setup.py
django_sortable/__init__.py
django_sortable/helpers.py
django_sortable/models.py
django_sortable/sortable.py
django_sortable.egg-info/PKG-INFO
django_sortable.egg-info/SOURCES.txt
django_sortable.egg-info/dependency_links.txt
django_sortable.egg-info/top_level.txt
django_sortable/templatetags/__init__.py
django_sortable/templatetags/sortable.py